.gitlab-ci.yml
.python-version
LICENSE.txt
MANIFEST.in
README.md
README.rst
helper.sh
setup.py
version.py
contrib/testinstall.sh
docs/HISTORY.txt
it4i/__init__.py
it4i.portal.clients.egg-info/PKG-INFO
it4i.portal.clients.egg-info/SOURCES.txt
it4i.portal.clients.egg-info/dependency_links.txt
it4i.portal.clients.egg-info/entry_points.txt
it4i.portal.clients.egg-info/namespace_packages.txt
it4i.portal.clients.egg-info/not-zip-safe
it4i.portal.clients.egg-info/requires.txt
it4i.portal.clients.egg-info/top_level.txt
it4i/portal/__init__.py
it4i/portal/clients/__init__.py
it4i/portal/clients/config.py
it4i/portal/clients/it4icheckaccess.py
it4i/portal/clients/it4idedicatedtime.py
it4i/portal/clients/it4ifree.py
it4i/portal/clients/it4ifsusage.py
it4i/portal/clients/it4imotd.py
it4i/portal/clients/it4iprojectfsusage.py
it4i/portal/clients/it4iuserfsusage.py
it4i/portal/clients/jsonlib.py
it4i/portal/clients/logger.py
it4i/portal/clients/conf/main.cfg-sample
it4i/portal/clients/templates/it4imotd.pt-sample