Metadata-Version: 1.1
Name: it4i.portal.clients
Version: 0.8.16
Summary: Client tools for accessing various client APIs of IT4I portals
Home-page: http://www.it4i.cz/
Author: IT4Innovations
Author-email: support@it4i.cz
License: BSD
Keywords: accounting api client extranet feed it4i it4innovations it4i.portal.clients it4i-portal-clients motd pbs portal rss tool
Platform: UNKNOWN
Classifier: Programming Language :: Python
